welcome_pkg/__init__.py
welcome_pkg/welcome_properties.py
pm_lib_exe96_welcome_message-0.0.2.dist-info/LICENSE
pm_lib_exe96_welcome_message-0.0.2.dist-info/METADATA
pm_lib_exe96_welcome_message-0.0.2.dist-info/WHEEL
pm_lib_exe96_welcome_message-0.0.2.dist-info/top_level.txt
pm_lib_exe96_welcome_message-0.0.2.dist-info/RECORD
