Metadata-Version: 2.1
Name: pm-lib-exe96-welcome-message
Version: 0.0.2
Summary: A small package which expects a value for name and outputs a welcome message
Home-page: https://github.com/parismoore/CPP_Project_2020
Author: Paris Moore
Author-email: x14485758@student.ncirl.ie
License: UNKNOWN
Platform: UNKNOWN
Classifier: Programming Language :: Python :: 3
Classifier: License :: OSI Approved :: MIT License
Classifier: Operating System :: OS Independent
Requires-Python: >=3.6
